MANIFEST.in
Makefile
README
setup.py
test/__init__.py
test/__init__.pyc
test/test_get_serializations.py
test/test_get_serializations.pyc
test/test_web_output.py
test/test_web_output.pyc
tiddlywebplugins/__init__.py
tiddlywebplugins/docs.py
tiddlywebplugins.docs.egg-info/PKG-INFO
tiddlywebplugins.docs.egg-info/SOURCES.txt
tiddlywebplugins.docs.egg-info/dependency_links.txt
tiddlywebplugins.docs.egg-info/namespace_packages.txt
tiddlywebplugins.docs.egg-info/not-zip-safe
tiddlywebplugins.docs.egg-info/requires.txt
tiddlywebplugins.docs.egg-info/top_level.txt
tiddlywebplugins/templates/tiddlywebdocs.html