Metadata-Version: 1.0
Name: tiddlywebplugins.docs
Version: 0.5
Summary: Automatic HTTP API documentation for TiddlyWeb
Home-page: http://pypi.python.org/pypi/tiddlywebplugins.docs
Author: Chris Dent
Author-email: cdent@peermore.com
License: UNKNOWN
Platform: Posix; MacOS X; Windows
